impexpr/__init__.py
impexpr/token_transformers.py
impexpr-0.0.5.dist-info/entry_points.txt
impexpr-0.0.5.dist-info/WHEEL
impexpr-0.0.5.dist-info/METADATA
impexpr-0.0.5.dist-info/RECORD
